ibis/__init__.py
ibis/ibis.py
ibis/config/template_coassemble.yaml
ibis/config/template_evaluate.yaml
ibis/workflow/coassemble.smk
ibis/workflow/evaluate.smk
ibis/workflow/env/aviary.yml
ibis/workflow/env/coverm.yml
ibis/workflow/env/fastp.yml
ibis/workflow/env/kingfisher.yml
ibis/workflow/env/prodigal.yml
ibis/workflow/env/r.yml
ibis/workflow/env/singlem.yml
ibis/workflow/scripts/aviary_commands.py
ibis/workflow/scripts/cluster_graph.py
ibis/workflow/scripts/collect_reference_bins.py
ibis/workflow/scripts/evaluate.py
ibis/workflow/scripts/is_interleaved.py
ibis/workflow/scripts/no_genomes.py
ibis/workflow/scripts/query_processing.py
ibis/workflow/scripts/summarise_coassemblies.py
ibis/workflow/scripts/target_elusive.py
ibis_genome-0.9.6.dist-info/LICENSE
ibis_genome-0.9.6.dist-info/METADATA
ibis_genome-0.9.6.dist-info/WHEEL
ibis_genome-0.9.6.dist-info/entry_points.txt
ibis_genome-0.9.6.dist-info/top_level.txt
ibis_genome-0.9.6.dist-info/RECORD
