Metadata-Version: 2.1
Name: ibis-genome
Version: 0.9.6
Summary: Ibis (Australian bin chicken) - targeted recovery of low abundance genomes through intelligent coassembly
Author-email: Samuel Aroney <samuel.aroney@outlook.com>
License: GNU GENERAL PUBLIC LICENSE
Project-URL: Homepage, https://github.com/AroneyS/ibis
Project-URL: Bug Tracker, https://github.com/AroneyS/ibis/issues
Classifier: Topic :: Scientific/Engineering :: Bio-Informatics
Requires-Python: >=3.10
License-File: LICENSE
Requires-Dist: snakemake >=6.0.5
Requires-Dist: mamba
Requires-Dist: networkx
Requires-Dist: bird-tool-utils
Requires-Dist: extern
Requires-Dist: ruamel.yaml >=0.15.99
Requires-Dist: polars
Requires-Dist: pyarrow
